fastapi_armor/__init__.py
fastapi_armor/header_map.py
fastapi_armor/middleware.py
fastapi_armor/presets.py
fastapi_armor-1.0.2.dist-info/METADATA
fastapi_armor-1.0.2.dist-info/WHEEL
fastapi_armor-1.0.2.dist-info/licenses/LICENSE
fastapi_armor-1.0.2.dist-info/RECORD
