Metadata-Version: 2.4
Name: fastapi-armor
Version: 1.0.2
Summary: HTTP security headers middleware for FastAPI.
Project-URL: Homepage, https://github.com/inanpy/fastapi-armor
Project-URL: Repository, https://github.com/inanpy/fastapi-armor
Author-email: Inan Delibas <inanndelibas@gmail.com>
License: MIT
License-File: LICENSE
Requires-Python: >=3.8
Requires-Dist: fastapi>=0.115.13
Requires-Dist: starlette<0.47.0,>=0.40.0
Provides-Extra: dev
Requires-Dist: httpx>=0.25; extra == 'dev'
Requires-Dist: pytest>=8.0; extra == 'dev'
